<?xml version="1.0" encoding="UTF-8"?>
<foxml:digitalObject VERSION="1.1" PID="rockhall:fixture_tape5"
xmlns:foxml="info:fedora/fedora-system:def/foxml#"
xmlns:xsi="http://www.w3.org/2001/XMLSchema-instance"
xsi:schemaLocation="info:fedora/fedora-system:def/foxml# http://www.fedora.info/definitions/1/0/foxml1-1.xsd">
<foxml:objectProperties>
<foxml:property NAME="info:fedora/fedora-system:def/model#state" VALUE="Active"/>
<foxml:property NAME="info:fedora/fedora-system:def/model#label" VALUE=""/>
<foxml:property NAME="info:fedora/fedora-system:def/model#ownerId" VALUE="fedoraAdmin"/>
<foxml:property NAME="info:fedora/fedora-system:def/model#createdDate" VALUE="2013-04-16T19:31:58.296Z"/>
<foxml:property NAME="info:fedora/fedora-system:def/view#lastModifiedDate" VALUE="2013-10-18T19:25:47.954Z"/>
</foxml:objectProperties>
<foxml:datastream ID="AUDIT" STATE="A" CONTROL_GROUP="X" VERSIONABLE="false">
<foxml:datastreamVersion ID="AUDIT.0" LABEL="Audit Trail for this object" CREATED="2013-04-16T19:31:58.296Z" MIMETYPE="text/xml" FORMAT_URI="info:fedora/fedora-system:format/xml.fedora.audit">
<foxml:xmlContent>
<audit:auditTrail xmlns:audit="info:fedora/fedora-system:def/audit#">
<audit:record ID="AUDREC1">
<audit:process type="Fedora API-M"/>
<audit:action>addDatastream</audit:action>
<audit:componentID>RELS-EXT</audit:componentID>
<audit:responsibility>fedoraAdmin</audit:responsibility>
<audit:date>2013-04-16T19:31:58.367Z</audit:date>
<audit:justification></audit:justification>
</audit:record>
<audit:record ID="AUDREC2">
<audit:process type="Fedora API-M"/>
<audit:action>addDatastream</audit:action>
<audit:componentID>descMetadata</audit:componentID>
<audit:responsibility>fedoraAdmin</audit:responsibility>
<audit:date>2013-04-16T19:31:58.496Z</audit:date>
<audit:justification></audit:justification>
</audit:record>
<audit:record ID="AUDREC3">
<audit:process type="Fedora API-M"/>
<audit:action>addDatastream</audit:action>
<audit:componentID>mediaInfo</audit:componentID>
<audit:responsibility>fedoraAdmin</audit:responsibility>
<audit:date>2013-04-16T19:31:58.527Z</audit:date>
<audit:justification></audit:justification>
</audit:record>
<audit:record ID="AUDREC4">
<audit:process type="Fedora API-M"/>
<audit:action>addDatastream</audit:action>
<audit:componentID>properties</audit:componentID>
<audit:responsibility>fedoraAdmin</audit:responsibility>
<audit:date>2013-04-16T19:31:58.561Z</audit:date>
<audit:justification></audit:justification>
</audit:record>
<audit:record ID="AUDREC5">
<audit:process type="Fedora API-M"/>
<audit:action>addDatastream</audit:action>
<audit:componentID>rightsMetadata</audit:componentID>
<audit:responsibility>fedoraAdmin</audit:responsibility>
<audit:date>2013-04-16T19:31:58.784Z</audit:date>
<audit:justification></audit:justification>
</audit:record>
<audit:record ID="AUDREC6">
<audit:process type="Fedora API-M"/>
<audit:action>modifyDatastreamByValue</audit:action>
<audit:componentID>descMetadata</audit:componentID>
<audit:responsibility>fedoraAdmin</audit:responsibility>
<audit:date>2013-04-16T19:31:58.819Z</audit:date>
<audit:justification></audit:justification>
</audit:record>
<audit:record ID="AUDREC7">
<audit:process type="Fedora API-M"/>
<audit:action>modifyDatastreamByValue</audit:action>
<audit:componentID>mediaInfo</audit:componentID>
<audit:responsibility>fedoraAdmin</audit:responsibility>
<audit:date>2013-04-16T19:31:58.852Z</audit:date>
<audit:justification></audit:justification>
</audit:record>
<audit:record ID="AUDREC8">
<audit:process type="Fedora API-M"/>
<audit:action>modifyDatastreamByValue</audit:action>
<audit:componentID>properties</audit:componentID>
<audit:responsibility>fedoraAdmin</audit:responsibility>
<audit:date>2013-04-16T19:31:58.887Z</audit:date>
<audit:justification></audit:justification>
</audit:record>
<audit:record ID="AUDREC9">
<audit:process type="Fedora API-M"/>
<audit:action>modifyDatastreamByValue</audit:action>
<audit:componentID>rightsMetadata</audit:componentID>
<audit:responsibility>fedoraAdmin</audit:responsibility>
<audit:date>2013-04-16T19:31:59.733Z</audit:date>
<audit:justification></audit:justification>
</audit:record>
<audit:record ID="AUDREC10">
<audit:process type="Fedora API-M"/>
<audit:action>modifyDatastreamByValue</audit:action>
<audit:componentID>descMetadata</audit:componentID>
<audit:responsibility>fedoraAdmin</audit:responsibility>
<audit:date>2013-04-16T19:31:59.830Z</audit:date>
<audit:justification></audit:justification>
</audit:record>
<audit:record ID="AUDREC11">
<audit:process type="Fedora API-M"/>
<audit:action>modifyDatastreamByValue</audit:action>
<audit:componentID>mediaInfo</audit:componentID>
<audit:responsibility>fedoraAdmin</audit:responsibility>
<audit:date>2013-04-16T19:31:59.860Z</audit:date>
<audit:justification></audit:justification>
</audit:record>
<audit:record ID="AUDREC12">
<audit:process type="Fedora API-M"/>
<audit:action>modifyDatastreamByValue</audit:action>
<audit:componentID>properties</audit:componentID>
<audit:responsibility>fedoraAdmin</audit:responsibility>
<audit:date>2013-04-16T19:31:59.894Z</audit:date>
<audit:justification></audit:justification>
</audit:record>
</audit:auditTrail>
</foxml:xmlContent>
</foxml:datastreamVersion>
</foxml:datastream>
<foxml:datastream ID="DC" STATE="A" CONTROL_GROUP="X" VERSIONABLE="true">
<foxml:datastreamVersion ID="DC1.0" LABEL="Dublin Core Record for this object" CREATED="2013-04-16T19:31:58.296Z" MIMETYPE="text/xml" FORMAT_URI="http://www.openarchives.org/OAI/2.0/oai_dc/" SIZE="351">
<foxml:contentDigest TYPE="SHA-1" DIGEST="394023bae87b3d7730f244e16f255dc34c12b4f5"/>
<foxml:xmlContent>
<oai_dc:dc xmlns:oai_dc="http://www.openarchives.org/OAI/2.0/oai_dc/" xmlns:dc="http://purl.org/dc/elements/1.1/" xmlns:xsi="http://www.w3.org/2001/XMLSchema-instance" xsi:schemaLocation="http://www.openarchives.org/OAI/2.0/oai_dc/ http://www.openarchives.org/OAI/2.0/oai_dc.xsd">
  <dc:identifier>rockhall:fixture_tape5</dc:identifier>
</oai_dc:dc>
</foxml:xmlContent>
</foxml:datastreamVersion>
</foxml:datastream>
<foxml:datastream ID="RELS-EXT" STATE="A" CONTROL_GROUP="X" VERSIONABLE="true">
<foxml:datastreamVersion ID="RELS-EXT.0" LABEL="Fedora Object-to-Object Relationship Metadata" CREATED="2013-04-16T19:31:58.367Z" MIMETYPE="application/rdf+xml" SIZE="431">
<foxml:contentDigest TYPE="SHA-1" DIGEST="5dc97c2dd836d440343cdcbf9d890ddb6ab22d00"/>
<foxml:xmlContent>
<rdf:RDF xmlns:ns0="info:fedora/fedora-system:def/model#" xmlns:ns1="info:fedora/fedora-system:def/relations-external#" xmlns:rdf="http://www.w3.org/1999/02/22-rdf-syntax-ns#">
  <rdf:Description rdf:about="info:fedora/rockhall:fixture_tape5">
    <ns0:hasModel rdf:resource="info:fedora/afmodel:ExternalVideo"></ns0:hasModel>
    <ns1:isPartOf rdf:resource="info:fedora/rrhof:525"></ns1:isPartOf>
  </rdf:Description>
</rdf:RDF>
</foxml:xmlContent>
</foxml:datastreamVersion>
</foxml:datastream>
<foxml:datastream ID="descMetadata" STATE="A" CONTROL_GROUP="X" VERSIONABLE="true">
<foxml:datastreamVersion ID="descMetadata.0" LABEL="" CREATED="2013-04-16T19:31:58.496Z" MIMETYPE="text/xml" SIZE="1079">
<foxml:contentDigest TYPE="SHA-1" DIGEST="6f0bf5e92e098bd5ed9107257780ba7170531c37"/>
<foxml:xmlContent>
<pbcoreInstantiation>
  <instantiationIdentifier annotation="Barcode" source="Rock and Roll Hall of Fame and Museum">39156042459755</instantiationIdentifier>
  <instantiationDate dateType="created">2001-05-03</instantiationDate>
  <instantiationPhysical source="PBCore instantiationPhysical">Betacam</instantiationPhysical>
  <instantiationStandard>NTSC</instantiationStandard>
  <instantiationLocation>Rock and Roll Hall of Fame and Museum,
2809 Woodland Ave.,
Cleveland, OH, 44115
216-515-1956
library@rockhall.org</instantiationLocation>
  <instantiationMediaType source="PBCore instantiationMediaType">Moving image</instantiationMediaType>
  <instantiationGenerations source="PBCore instantiationGenerations">Original</instantiationGenerations>
  <instantiationColors source="PBCore instantiationColors">Color</instantiationColors>
  <instantiationLanguage ref="http://www.loc.gov/standards/iso639-2/php/code_list.php" source="ISO 639.2">eng</instantiationLanguage>
  <instantiationRights>
    <rightsSummary></rightsSummary>
  </instantiationRights>
</pbcoreInstantiation>
</foxml:xmlContent>
</foxml:datastreamVersion>
<foxml:datastreamVersion ID="descMetadata.1" LABEL="" CREATED="2013-04-16T19:31:58.819Z" MIMETYPE="text/xml" SIZE="1079">
<foxml:contentDigest TYPE="SHA-1" DIGEST="6f0bf5e92e098bd5ed9107257780ba7170531c37"/>
<foxml:xmlContent>
<pbcoreInstantiation>
  <instantiationIdentifier annotation="Barcode" source="Rock and Roll Hall of Fame and Museum">39156042459755</instantiationIdentifier>
  <instantiationDate dateType="created">2001-05-03</instantiationDate>
  <instantiationPhysical source="PBCore instantiationPhysical">Betacam</instantiationPhysical>
  <instantiationStandard>NTSC</instantiationStandard>
  <instantiationLocation>Rock and Roll Hall of Fame and Museum,
2809 Woodland Ave.,
Cleveland, OH, 44115
216-515-1956
library@rockhall.org</instantiationLocation>
  <instantiationMediaType source="PBCore instantiationMediaType">Moving image</instantiationMediaType>
  <instantiationGenerations source="PBCore instantiationGenerations">Original</instantiationGenerations>
  <instantiationColors source="PBCore instantiationColors">Color</instantiationColors>
  <instantiationLanguage ref="http://www.loc.gov/standards/iso639-2/php/code_list.php" source="ISO 639.2">eng</instantiationLanguage>
  <instantiationRights>
    <rightsSummary></rightsSummary>
  </instantiationRights>
</pbcoreInstantiation>
</foxml:xmlContent>
</foxml:datastreamVersion>
<foxml:datastreamVersion ID="descMetadata.2" LABEL="" CREATED="2013-04-16T19:31:59.830Z" MIMETYPE="text/xml" SIZE="1079">
<foxml:contentDigest TYPE="SHA-1" DIGEST="6f0bf5e92e098bd5ed9107257780ba7170531c37"/>
<foxml:xmlContent>
<pbcoreInstantiation>
  <instantiationIdentifier annotation="Barcode" source="Rock and Roll Hall of Fame and Museum">39156042459755</instantiationIdentifier>
  <instantiationDate dateType="created">2001-05-03</instantiationDate>
  <instantiationPhysical source="PBCore instantiationPhysical">Betacam</instantiationPhysical>
  <instantiationStandard>NTSC</instantiationStandard>
  <instantiationLocation>Rock and Roll Hall of Fame and Museum,
2809 Woodland Ave.,
Cleveland, OH, 44115
216-515-1956
library@rockhall.org</instantiationLocation>
  <instantiationMediaType source="PBCore instantiationMediaType">Moving image</instantiationMediaType>
  <instantiationGenerations source="PBCore instantiationGenerations">Original</instantiationGenerations>
  <instantiationColors source="PBCore instantiationColors">Color</instantiationColors>
  <instantiationLanguage ref="http://www.loc.gov/standards/iso639-2/php/code_list.php" source="ISO 639.2">eng</instantiationLanguage>
  <instantiationRights>
    <rightsSummary></rightsSummary>
  </instantiationRights>
</pbcoreInstantiation>
</foxml:xmlContent>
</foxml:datastreamVersion>
</foxml:datastream>
<foxml:datastream ID="mediaInfo" STATE="A" CONTROL_GROUP="X" VERSIONABLE="true">
<foxml:datastreamVersion ID="mediaInfo.0" LABEL="" CREATED="2013-04-16T19:31:58.527Z" MIMETYPE="text/xml" SIZE="13">
<foxml:contentDigest TYPE="SHA-1" DIGEST="07315aebd3da4beb4f679dc4efb4c389f3ff436b"/>
<foxml:xmlContent>
<xml></xml>
</foxml:xmlContent>
</foxml:datastreamVersion>
<foxml:datastreamVersion ID="mediaInfo.1" LABEL="" CREATED="2013-04-16T19:31:58.852Z" MIMETYPE="text/xml" SIZE="13">
<foxml:contentDigest TYPE="SHA-1" DIGEST="07315aebd3da4beb4f679dc4efb4c389f3ff436b"/>
<foxml:xmlContent>
<xml></xml>
</foxml:xmlContent>
</foxml:datastreamVersion>
<foxml:datastreamVersion ID="mediaInfo.2" LABEL="" CREATED="2013-04-16T19:31:59.860Z" MIMETYPE="text/xml" SIZE="13">
<foxml:contentDigest TYPE="SHA-1" DIGEST="07315aebd3da4beb4f679dc4efb4c389f3ff436b"/>
<foxml:xmlContent>
<xml></xml>
</foxml:xmlContent>
</foxml:datastreamVersion>
</foxml:datastream>
<foxml:datastream ID="properties" STATE="A" CONTROL_GROUP="X" VERSIONABLE="true">
<foxml:datastreamVersion ID="properties.0" LABEL="" CREATED="2013-04-16T19:31:58.561Z" MIMETYPE="text/xml" SIZE="140">
<foxml:contentDigest TYPE="SHA-1" DIGEST="27a9a2c23eff60172ae415d1fc923b1afbe31cc3"/>
<foxml:xmlContent>
<fields>
  <collection></collection>
  <depositor></depositor>
  <notes></notes>
  <access></access>
  <submission></submission>
</fields>
</foxml:xmlContent>
</foxml:datastreamVersion>
<foxml:datastreamVersion ID="properties.1" LABEL="" CREATED="2013-04-16T19:31:58.887Z" MIMETYPE="text/xml" SIZE="140">
<foxml:contentDigest TYPE="SHA-1" DIGEST="27a9a2c23eff60172ae415d1fc923b1afbe31cc3"/>
<foxml:xmlContent>
<fields>
  <collection></collection>
  <depositor></depositor>
  <notes></notes>
  <access></access>
  <submission></submission>
</fields>
</foxml:xmlContent>
</foxml:datastreamVersion>
<foxml:datastreamVersion ID="properties.2" LABEL="" CREATED="2013-04-16T19:31:59.894Z" MIMETYPE="text/xml" SIZE="140">
<foxml:contentDigest TYPE="SHA-1" DIGEST="27a9a2c23eff60172ae415d1fc923b1afbe31cc3"/>
<foxml:xmlContent>
<fields>
  <collection></collection>
  <depositor></depositor>
  <notes></notes>
  <access></access>
  <submission></submission>
</fields>
</foxml:xmlContent>
</foxml:datastreamVersion>
</foxml:datastream>
<foxml:datastream ID="rightsMetadata" STATE="A" CONTROL_GROUP="X" VERSIONABLE="true">
<foxml:datastreamVersion ID="rightsMetadata.0" LABEL="" CREATED="2013-04-16T19:31:58.784Z" MIMETYPE="text/xml" SIZE="661">
<foxml:contentDigest TYPE="SHA-1" DIGEST="6f42599f33a32aee0cd4e4804b5370ff9d892008"/>
<foxml:xmlContent>
<rightsMetadata xmlns="http://hydra-collab.stanford.edu/schemas/rightsMetadata/v1" version="0.1">
  <copyright>
    <human type="title"></human>
    <human type="description"></human>
    <machine type="uri"></machine>
  </copyright>
  <access type="discover">
    <human></human>
    <machine></machine>
  </access>
  <access type="read">
    <human></human>
    <machine>
      <group>donor</group>
    </machine>
  </access>
  <access type="edit">
    <human></human>
    <machine>
      <group>archivist</group>
      <group>reviewer</group>
    </machine>
  </access>
  <embargo>
    <human></human>
    <machine></machine>
  </embargo>
</rightsMetadata>
</foxml:xmlContent>
</foxml:datastreamVersion>
<foxml:datastreamVersion ID="rightsMetadata.1" LABEL="" CREATED="2013-04-16T19:31:59.733Z" MIMETYPE="text/xml" SIZE="661">
<foxml:contentDigest TYPE="SHA-1" DIGEST="6f42599f33a32aee0cd4e4804b5370ff9d892008"/>
<foxml:xmlContent>
<rightsMetadata xmlns="http://hydra-collab.stanford.edu/schemas/rightsMetadata/v1" version="0.1">
  <copyright>
    <human type="title"></human>
    <human type="description"></human>
    <machine type="uri"></machine>
  </copyright>
  <access type="discover">
    <human></human>
    <machine></machine>
  </access>
  <access type="read">
    <human></human>
    <machine>
      <group>donor</group>
    </machine>
  </access>
  <access type="edit">
    <human></human>
    <machine>
      <group>archivist</group>
      <group>reviewer</group>
    </machine>
  </access>
  <embargo>
    <human></human>
    <machine></machine>
  </embargo>
</rightsMetadata>
</foxml:xmlContent>
</foxml:datastreamVersion>
</foxml:datastream>
</foxml:digitalObject>